{
  "chunk_id": "doc_001_chunk_0001",
  "source_document_id": "doc_001",
  "source_file": "Действия на сервисном выезде.docx",
  "topic": "Сервисный выезд",
  "roles": [
    "монтажник",
    "электрик",
    "инженер ГО"
  ],
  "section_path": [
    "Методика проведения сервисного выезда по выравниванию АКБ."
  ],
  "text": "**Методика проведения сервисного выезда по выравниванию АКБ.**\n\n- Проверка затяжки проводов в клеммных терминалах инвертора, щитах.\n\n- Продувка инвертора(при выключенном инверторе).\n\n- Снятие крышки инвертора и повторная продувка(при необходимости).\n\n- Проверка настроек инвертора.\n\n- Замер напряжения на АКБ.\n\n- Проверка болтов на АКБ(затяжка, состояние).\n\n- Смазка болтов АКБ(при необходимости).\n\n- Проверка работы инвертора во всех режимах.\n\n- Проверка работы балансира.\n\n- Выравнивание АКБ.\n\n- Проверка напряжения на АКБ.\n\n- Фотографии и видеозаписи настроек оборудования, измерений, выполненной работы.",
  "related_image_ids": [],
  "excluded_image_ids": [],
  "previous_context": "",
  "next_context": "",
  "needs_review": false,
  "review_reasons": [],
  "suggested_topic": "service_visit",
  "suggested_roles": [
    "electrician",
    "hq_engineer",
    "installer"
  ]
}
